dyools/__init__.py
dyools/cli_deploy.py
dyools/cli_etl.py
dyools/cli_help.py
dyools/cli_job.py
dyools/cli_po.py
dyools/cli_rpc.py
dyools/cli_sign.py
dyools/cli_todo.py
dyools/cli_tool.py
dyools/cli_ws_agent.py
dyools/cli_xml.py
dyools/decorators.py
dyools/klass_connector.py
dyools/klass_consumer.py
dyools/klass_convert.py
dyools/klass_counter.py
dyools/klass_csv_connector.py
dyools/klass_csv_job.py
dyools/klass_data.py
dyools/klass_dataframe.py
dyools/klass_date.py
dyools/klass_default_value.py
dyools/klass_df.py
dyools/klass_eval.py
dyools/klass_inspect.py
dyools/klass_is.py
dyools/klass_job.py
dyools/klass_logger.py
dyools/klass_odoo_connector.py
dyools/klass_odoo_env.py
dyools/klass_odoo_job.py
dyools/klass_odoo_mixin.py
dyools/klass_odoo_rpc.py
dyools/klass_odoo_simple_migrate.py
dyools/klass_offset_limit.py
dyools/klass_operator.py
dyools/klass_path.py
dyools/klass_print.py
dyools/klass_progress_bar.py
dyools/klass_queue.py
dyools/klass_random.py
dyools/klass_sample.py
dyools/klass_sequence.py
dyools/klass_serie.py
dyools/klass_sftp.py
dyools/klass_slice.py
dyools/klass_str.py
dyools/klass_table.py
dyools/klass_tool.py
dyools/klass_ws.py
dyools/klass_xlsreader.py
dyools/klass_xlswriter.py
dyools/klass_xml.py
dyools/klass_yaml_config.py
dyools-0.21.3.dist-info/METADATA
dyools-0.21.3.dist-info/WHEEL
dyools-0.21.3.dist-info/top_level.txt
dyools-0.21.3.dist-info/zip-safe
dyools-0.21.3.dist-info/RECORD
